{
  "currentUser": {
    "id": "22",
    "isLogged": true
  },
  "users": [
    {
      "id": "22",
      "login": "Oskar",
      "password": "root",
      "followers": [],
      "following": []
    },
    {
      "id": "c66d10ff-87f2-4639-a580-a458e12cf42d",
      "login": "Robert",
      "password": "123",
      "followers": [],
      "following": []
    }
  ],
  "posts": [
    {
      "id": "efbe19ea-4005-4811-8fed-5371721df970",
      "title": "test",
      "desc": "test",
      "img": "121",
      "likes": [],
      "ownerID": "22"
    },
    {
      "id": "b00e4e95-c71c-460b-ba57-3c03f47a335d",
      "title": "tes",
      "desc": "ts",
      "img": "te",
      "likes": [
        "22"
      ],
      "ownerID": "22"
    }
  ],
  "comments": [
    {
      "id": "15338917-280b-4df2-bac5-1db1ea3c818e",
      "ownerID": "22",
      "postID": "efbe19ea-4005-4811-8fed-5371721df970",
      "comment": "hej"
    }
  ]
}